{
    "genres": [
        {
            "genre": "Les années 1950",
            "media": [
                {
                    "title": "Only you",
                    "music": "6367_ThePlatters_Onlyyou_1956.mp3",
                    "artist": {
                        "name": "The Platters"
                    }
                },
                {
                    "title": "Down by the riverside",
                    "music": "3684_GoldenGateQuart_Downbytheriverside_1955.mp3",
                    "artist": {
                        "name": "Golden Gate Quartet"
                    }
                },
                {
                    "title": "Shadrack",
                    "music": "3690_GoldenGateQuart_Shadrack_1955.mp3",
                    "artist": {
                        "name": "Golden Gate Quartet"
                    }
                },
                {
                    "title": "Didn't it rain",
                    "music": "3683_GoldenGateQuart_Didntitrain_1955.mp3",
                    "artist": {
                        "name": "Golden Gate Quartet"
                    }
                },
                {
                    "title": "Swing low, sweet chariot",
                    "music": "3692_GoldenGateQuart_Swinglowsweetchariot_1955.mp3",
                    "artist": {
                        "name": "Golden Gate Quartet"
                    }
                },
                {
                    "title": "Lullaby of birdland",
                    "music": "2991_EllaFitzgerald_Lullabyofbirdland_1955.mp3",
                    "artist": {
                        "name": "Ella Fitzgerald"
                    }
                },
                {
                    "title": "Mack the Knife",
                    "music": "33555_LouisArmstrong_MacktheKnife_1959.mp3",
                    "artist": {
                        "name": "Louis Armstrong"
                    }
                },
                {
                    "title": "You send me",
                    "music": "7060_SamCooke_Yousendme_1958.mp3",
                    "artist": {
                        "name": "Sam Cooke"
                    }
                },
                {
                    "title": "Say 'Si Si'",
                    "music": "55905_TheAndrewsSiste_SaySiSi_1955.mp3",
                    "artist": {
                        "name": "The Andrews Sisters"
                    }
                },
                {
                    "title": "Please, please, please",
                    "music": "4106_JamesBrown_Pleasepleaseplease_1959.mp3",
                    "artist": {
                        "name": "James Brown"
                    }
                },
                {
                    "title": "Down by the riverside",
                    "music": "3684_GoldenGateQuart_Downbytheriverside_1955.mp3",
                    "artist": {
                        "name": "Golden Gate Quartet"
                    }
                },
                {
                    "title": "Shadrack",
                    "music": "3690_GoldenGateQuart_Shadrack_1955.mp3",
                    "artist": {
                        "name": "Golden Gate Quartet"
                    }
                },
                {
                    "title": "Didn't it rain",
                    "music": "3683_GoldenGateQuart_Didntitrain_1955.mp3",
                    "artist": {
                        "name": "Golden Gate Quartet"
                    }
                },
                {
                    "title": "Swing low, sweet chariot",
                    "music": "3692_GoldenGateQuart_Swinglowsweetchariot_1955.mp3",
                    "artist": {
                        "name": "Golden Gate Quartet"
                    }
                },
                {
                    "title": "Elijah",
                    "music": "3685_GoldenGateQuart_Elijah_1955.mp3",
                    "artist": {
                        "name": "Golden Gate Quartet"
                    }
                },
                {
                    "title": "Blue Moon",
                    "music": "31428_BillieHoliday_BlueMoon_1956.mp3",
                    "artist": {
                        "name": "Billie Holiday"
                    }
                },
                {
                    "title": "Spiral",
                    "music": "4416_JohnColtrane_Spiral_1959.mp3",
                    "artist": {
                        "name": "John Coltrane"
                    }
                },
                {
                    "title": "I'm In The Mood",
                    "music": "36150_JohnLeeHooker_ImInTheMood_1954.mp3",
                    "artist": {
                        "name": "John Lee Hooker"
                    }
                },
                {
                    "title": "Down by the riverside",
                    "music": "3684_GoldenGateQuart_Downbytheriverside_1955.mp3",
                    "artist": {
                        "name": "Golden Gate Quartet"
                    }
                },
                {
                    "title": "Shadrack",
                    "music": "3690_GoldenGateQuart_Shadrack_1955.mp3",
                    "artist": {
                        "name": "Golden Gate Quartet"
                    }
                },
                {
                    "title": "Didn't it rain",
                    "music": "3683_GoldenGateQuart_Didntitrain_1955.mp3",
                    "artist": {
                        "name": "Golden Gate Quartet"
                    }
                },
                {
                    "title": "Swing low, sweet chariot",
                    "music": "3692_GoldenGateQuart_Swinglowsweetchariot_1955.mp3",
                    "artist": {
                        "name": "Golden Gate Quartet"
                    }
                },
                {
                    "title": "Elijah",
                    "music": "3685_GoldenGateQuart_Elijah_1955.mp3",
                    "artist": {
                        "name": "Golden Gate Quartet"
                    }
                },
                {
                    "title": "Invisible hands",
                    "music": "3687_GoldenGateQuart_Invisiblehands_1955.mp3",
                    "artist": {
                        "name": "Golden Gate Quartet"
                    }
                },
                {
                    "title": "Summertime",
                    "music": "8794_OscarPeterson_Summertime_1959.mp3",
                    "artist": {
                        "name": "Oscar Peterson"
                    }
                },
                {
                    "title": "Autumn leaves",
                    "music": "1072_BillEvans_Autumnleaves_1959.mp3",
                    "artist": {
                        "name": "Bill Evans"
                    }
                }
            ]
        },
        {
            "genre": "Les années 1960",
            "media": [
                {
                    "title": "Baby, Baby, Baby",
                    "music": "43945_ArethaFranklin_BabyBabyBaby_1967.mp3",
                    "artist": {
                        "name": "Aretha Franklin"
                    }
                },
                {
                    "title": "Sweet sixteen",
                    "music": "808_B.B.King_Sweetsixteen_1964.mp3",
                    "artist": {
                        "name": "B.B. King"
                    }
                },
                {
                    "title": "Boom Boom",
                    "music": "4434_JohnLeeHookerSt_BoomBoom_1962.mp3",
                    "artist": {
                        "name": "John Lee Hooker & Stevie Ray Vaughn"
                    }
                },
                {
                    "title": "Oh happy day",
                    "music": "39457_GoldenGateQuart_Ohhappyday_1960.mp3",
                    "artist": {
                        "name": "Golden Gate Quartet"
                    }
                },
                {
                    "title": "Can Anyone Explain",
                    "music": "32784_EllaFitzgerald_CanAnyoneExplain_1960.mp3",
                    "artist": {
                        "name": "Ella Fitzgerald"
                    }
                },
                {
                    "title": "Hello, Dolly",
                    "music": "10770_LouisArmstrong_HelloDolly_1964.mp3",
                    "artist": {
                        "name": "Louis Armstrong"
                    }
                },
                {
                    "title": "So Danço Samba (I Only Dance Samba)",
                    "music": "20543_StanGetzJoaoGil_SoDan231oSamba(IOnly_1963.mp3",
                    "artist": {
                        "name": "Stan Getz & Joao Gilberto"
                    }
                },
                {
                    "title": "Under The Mango Tree",
                    "music": "59960_Dr.No_UnderTheMangoTree_1962.mp3",
                    "artist": {
                        "name": "Dr. No"
                    }
                },
                {
                    "title": "Obe",
                    "music": "105460_FelaKuti_Obe_1969.mp3",
                    "artist": {
                        "name": "Fela Kuti"
                    }
                },
                {
                    "title": "All In One",
                    "music": "45751_BobMarley_AllInOne_1969.mp3",
                    "artist": {
                        "name": "Bob Marley"
                    }
                },
                {
                    "title": "My Girl",
                    "music": "54150_OtisRedding_MyGirl_1966.mp3",
                    "artist": {
                        "name": "Otis Redding"
                    }
                },
                {
                    "title": "Your precious love",
                    "music": "5326_MarvinGaye_Yourpreciouslove_1967.mp3",
                    "artist": {
                        "name": "Marvin Gaye"
                    }
                },
                {
                    "title": "Cruisin",
                    "music": "54403_SmokeyRobinson_Cruisin_1968.mp3",
                    "artist": {
                        "name": "Smokey Robinson"
                    }
                },
                {
                    "title": "Coming into Los Angeles",
                    "music": "350_ArloGuthrie_ComingintoLosAngeles_1969.mp3",
                    "artist": {
                        "name": "Arlo Guthrie"
                    }
                },
                {
                    "title": "Act Naturally",
                    "music": "72299_BuckOwens_ActNaturally_1963.mp3",
                    "artist": {
                        "name": "Buck Owens"
                    }
                },
                {
                    "title": "Love Me Do",
                    "music": "21080_TheBeatles_LoveMeDo_1963.mp3",
                    "artist": {
                        "name": "The Beatles"
                    }
                },
                {
                    "title": "Sunny afternoon",
                    "music": "4723_TheKinks_Sunnyafternoon_1966.mp3",
                    "artist": {
                        "name": "The Kinks"
                    }
                },
                {
                    "title": "California Dreamin'",
                    "music": "5217_TheMamasandTheP_CaliforniaDreamin_1966.mp3",
                    "artist": {
                        "name": "The Mamas and The Papas"
                    }
                },
                {
                    "title": "Do You Want To Know A Secret",
                    "music": "21083_TheBeatles_DoYouWantToKnowASecr_1963.mp3",
                    "artist": {
                        "name": "The Beatles"
                    }
                },
                {
                    "title": "A Fine Romance",
                    "music": "24121_MarilynMonroe_AFineRomance_1960.mp3",
                    "artist": {
                        "name": "Marilyn Monroe"
                    }
                },
                {
                    "title": "Cabaret",
                    "music": "112636_BrendaLee_Cabaret_1968.mp3",
                    "artist": {
                        "name": "Brenda Lee"
                    }
                },
                {
                    "title": "My girl",
                    "music": "7763_TheTemptations_Mygirl_1965.mp3",
                    "artist": {
                        "name": "The Temptations"
                    }
                },
                {
                    "title": "Everybody is a star",
                    "music": "7364_SlyandtheFamily_Everybodyisastar_1969.mp3",
                    "artist": {
                        "name": "Sly and the Family Stone"
                    }
                },
                {
                    "title": "Down In The Gutter, But Free",
                    "music": "76951_CannedHeat_DownInTheGutterButFr_1969.mp3",
                    "artist": {
                        "name": "Canned Heat"
                    }
                },
                {
                    "title": "Country Girl",
                    "music": "144054_B.B.King_CountryGirl_1968.mp3",
                    "artist": {
                        "name": "B.B. King"
                    }
                },
                {
                    "title": "One Monkey Don't Stop No Show",
                    "music": "36126_JoeTex_OneMonkeyDontStopNoS_1966.mp3",
                    "artist": {
                        "name": "Joe Tex"
                    }
                },
                {
                    "title": "A man of many words",
                    "music": "13167_JuniorWells_Amanofmanywords_1964.mp3",
                    "artist": {
                        "name": "Junior Wells"
                    }
                },
                {
                    "title": "Who walks in when I walk out?",
                    "music": "32786_EllaFitzgerald_WhowalksinwhenIwalko_1960.mp3",
                    "artist": {
                        "name": "Ella Fitzgerald"
                    }
                },
                {
                    "title": "Incarnation",
                    "music": "34251_PepperAdams_Incarnation_1963.mp3",
                    "artist": {
                        "name": "Pepper Adams"
                    }
                },
                {
                    "title": "Samba Em Prelúdio",
                    "music": "8165_ViniciusdeMorae_SambaEmPrel250dio_1963.mp3",
                    "artist": {
                        "name": "Vinicius de Moraes"
                    }
                },
                {
                    "title": "April Come She Will",
                    "music": "37483_TheGraduate_AprilComeSheWill_1968.mp3",
                    "artist": {
                        "name": "The Graduate"
                    }
                },
                {
                    "title": "I Got To Get To California",
                    "music": "62610_MarvinGaye_IGotToGetToCaliforni_1969.mp3",
                    "artist": {
                        "name": "Marvin Gaye"
                    }
                },
                {
                    "title": "The weight",
                    "music": "62987_TheStapleSinger_Theweight_1968.mp3",
                    "artist": {
                        "name": "The Staple Singers"
                    }
                },
                {
                    "title": "Act Naturally",
                    "music": "72299_BuckOwens_ActNaturally_1963.mp3",
                    "artist": {
                        "name": "Buck Owens"
                    }
                },
                {
                    "title": "Black mountain side",
                    "music": "4877_LedZeppelin_Blackmountainside_1969.mp3",
                    "artist": {
                        "name": "Led Zeppelin"
                    }
                },
                {
                    "title": "More blues",
                    "music": "6313_PinkFloyd_Moreblues_1969.mp3",
                    "artist": {
                        "name": "Pink Floyd"
                    }
                },
                {
                    "title": "When Love Goes Wrong Nothing Goes Right",
                    "music": "24120_MarilynMonroe_WhenLoveGoesWrongNot_1960.mp3",
                    "artist": {
                        "name": "Marilyn Monroe"
                    }
                },
                {
                    "title": "(I Can't Get No) Satisfaction @ Live Paris",
                    "music": "43951_ArethaFranklin_(ICantGetNo)Satisfac_1968.mp3",
                    "artist": {
                        "name": "Aretha Franklin"
                    }
                },
                {
                    "title": "Money Won't Change You",
                    "music": "43965_ArethaFranklin_MoneyWontChangeYou_1968.mp3",
                    "artist": {
                        "name": "Aretha Franklin"
                    }
                },
                {
                    "title": "Country Girl",
                    "music": "144054_B.B.King_CountryGirl_1968.mp3",
                    "artist": {
                        "name": "B.B. King"
                    }
                },
                {
                    "title": "King of the Road",
                    "music": "36142_JoeTex_KingoftheRoad_1966.mp3",
                    "artist": {
                        "name": "Joe Tex"
                    }
                },
                {
                    "title": "I've forgotten more than you ever know about him",
                    "music": "3221_EstherPhillips_Iveforgottenmorethan_1966.mp3",
                    "artist": {
                        "name": "Esther Phillips"
                    }
                },
                {
                    "title": "Manana De Carnaval",
                    "music": "98491_PacoDeLucia_MananaDeCarnaval_1967.mp3",
                    "artist": {
                        "name": "Paco De Lucia"
                    }
                },
                {
                    "title": "Quero Esquecer Você",
                    "music": "40870_JorgeBen_QueroEsquecerVoc234_1963.mp3",
                    "artist": {
                        "name": "Jorge Ben"
                    }
                },
                {
                    "title": "Les Moulins De Mon Coeur",
                    "music": "37573_TheThomasCrownA_LesMoulinsDeMonCoeur_1968.mp3",
                    "artist": {
                        "name": "The Thomas Crown Affair"
                    }
                },
                {
                    "title": "Obe",
                    "music": "105460_FelaKuti_Obe_1969.mp3",
                    "artist": {
                        "name": "Fela Kuti"
                    }
                },
                {
                    "title": "Think",
                    "music": "554_ArethaFranklin_Think_1968.mp3",
                    "artist": {
                        "name": "Aretha Franklin"
                    }
                },
                {
                    "title": "River deep, montain high",
                    "music": "3936_IkeandTinaTurne_Riverdeepmontainhigh_1966.mp3",
                    "artist": {
                        "name": "Ike and Tina Turner"
                    }
                },
                {
                    "title": "Ain't no mountain high enough",
                    "music": "5342_MarvinGaye_Aintnomountainhighen_1967.mp3",
                    "artist": {
                        "name": "Marvin Gaye"
                    }
                },
                {
                    "title": "I say a little pray for you",
                    "music": "543_ArethaFranklin_Isayalittleprayforyo_1969.mp3",
                    "artist": {
                        "name": "Aretha Franklin"
                    }
                },
                {
                    "title": "Land of 1000 dances",
                    "music": "8247_WilsonPickett_Landof1000dances_1966.mp3",
                    "artist": {
                        "name": "Wilson Pickett"
                    }
                },
                {
                    "title": "Hey Gyp ( Dig The Slowness )",
                    "music": "60448_Donovan_HeyGyp(DigTheSlownes_1965.mp3",
                    "artist": {
                        "name": "Donovan"
                    }
                },
                {
                    "title": "Pay The Price",
                    "music": "95364_BuffaloSpringfi_PayThePrice_1966.mp3",
                    "artist": {
                        "name": "Buffalo Springfield"
                    }
                },
                {
                    "title": "Tombstone Blues",
                    "music": "46874_BobDylan_TombstoneBlues_1965.mp3",
                    "artist": {
                        "name": "Bob Dylan"
                    }
                },
                {
                    "title": "The loner",
                    "music": "5802_NeilYoung_Theloner_1969.mp3",
                    "artist": {
                        "name": "Neil Young"
                    }
                },
                {
                    "title": "Act Naturally",
                    "music": "72299_BuckOwens_ActNaturally_1963.mp3",
                    "artist": {
                        "name": "Buck Owens"
                    }
                }
            ]
        },
        {
            "genre": "Les années 1970",
            "media": [
                {
                    "title": "Mother and child reunion",
                    "music": "6202_PaulSimon_Motherandchildreunio_1972.mp3",
                    "artist": {
                        "name": "Paul Simon"
                    }
                },
                {
                    "title": "Strange magic",
                    "music": "2968_ElectricLightOr_Strangemagic_1975.mp3",
                    "artist": {
                        "name": "Electric Light Orchestra"
                    }
                },
                {
                    "title": "No Woman No Cry",
                    "music": "75382_BoneyM_NoWomanNoCry_1976.mp3",
                    "artist": {
                        "name": "Boney M"
                    }
                },
                {
                    "title": "I love to love",
                    "music": "7837_TinaCharles_Ilovetolove_1977.mp3",
                    "artist": {
                        "name": "Tina Charles"
                    }
                },
                {
                    "title": "I Want Your Love",
                    "music": "72322_Chic_IWantYourLove_1978.mp3",
                    "artist": {
                        "name": "Chic"
                    }
                },
                {
                    "title": "Highway to hell",
                    "music": "70_ACDC_Highwaytohell_1979.mp3",
                    "artist": {
                        "name": "AC/DC"
                    }
                },
                {
                    "title": "Girls Got Rhythm",
                    "music": "41072_ACDC_GirlsGotRhythm_1979.mp3",
                    "artist": {
                        "name": "AC/DC"
                    }
                },
                {
                    "title": "Sweet emotion",
                    "music": "116_Aerosmith_Sweetemotion_1975.mp3",
                    "artist": {
                        "name": "Aerosmith"
                    }
                },
                {
                    "title": "Send Me Your Pillow",
                    "music": "76981_CannedHeat_SendMeYourPillow_1971.mp3",
                    "artist": {
                        "name": "Canned Heat"
                    }
                },
                {
                    "title": "Love Scene",
                    "music": "37715_ZabriskiePoint_LoveScene_1970.mp3",
                    "artist": {
                        "name": "Zabriskie Point"
                    }
                },
                {
                    "title": "Relax Baby Be Cool",
                    "music": "70577_SergeGainsbourg_RelaxBabyBeCool_1979.mp3",
                    "artist": {
                        "name": "Serge Gainsbourg"
                    }
                },
                {
                    "title": "Words Of Wisdom",
                    "music": "80868_DennisBrown_WordsOfWisdom_1979.mp3",
                    "artist": {
                        "name": "Dennis Brown"
                    }
                },
                {
                    "title": "What's Happening Brother",
                    "music": "62613_MarvinGaye_WhatsHappeningBrothe_1971.mp3",
                    "artist": {
                        "name": "Marvin Gaye"
                    }
                },
                {
                    "title": "Joan Of Arc",
                    "music": "55469_LeonardCohen_JoanOfArc_1971.mp3",
                    "artist": {
                        "name": "Leonard Cohen"
                    }
                },
                {
                    "title": "Woodstock",
                    "music": "55229_JoniMitchell_Woodstock_1970.mp3",
                    "artist": {
                        "name": "Joni Mitchell"
                    }
                },
                {
                    "title": "Place To Be",
                    "music": "130293_NickDrake_PlaceToBe_1972.mp3",
                    "artist": {
                        "name": "Nick Drake"
                    }
                },
                {
                    "title": "Stand By Me",
                    "music": "36514_RyCooder_StandByMe_1976.mp3",
                    "artist": {
                        "name": "Ry Cooder"
                    }
                },
                {
                    "title": "Let your love flow",
                    "music": "145598_TheBellamyBroth_Letyourloveflow_1976.mp3",
                    "artist": {
                        "name": "The Bellamy Brothers"
                    }
                },
                {
                    "title": "There Goes My Everything",
                    "music": "56705_ElvisPresley_ThereGoesMyEverythin_1971.mp3",
                    "artist": {
                        "name": "Elvis Presley"
                    }
                },
                {
                    "title": "Make the World Go Away",
                    "music": "56710_ElvisPresley_MaketheWorldGoAway_1971.mp3",
                    "artist": {
                        "name": "Elvis Presley"
                    }
                },
                {
                    "title": "Rifle Range",
                    "music": "72719_Blondie_RifleRange_1976.mp3",
                    "artist": {
                        "name": "Blondie"
                    }
                },
                {
                    "title": "Vanina",
                    "music": "2412_Dave_Vanina_1974.mp3",
                    "artist": {
                        "name": "Dave"
                    }
                },
                {
                    "title": "Only the Good Die Young",
                    "music": "55013_BillyJoel_OnlytheGoodDieYoung_1977.mp3",
                    "artist": {
                        "name": "Billy Joel"
                    }
                },
                {
                    "title": "Hot stuff",
                    "music": "2789_DonnaSummer_Hotstuff_1979.mp3",
                    "artist": {
                        "name": "Donna Summer"
                    }
                },
                {
                    "title": "Heaven knows",
                    "music": "2788_DonnaSummer_Heavenknows_1978.mp3",
                    "artist": {
                        "name": "Donna Summer"
                    }
                },
                {
                    "title": "Funkytown",
                    "music": "5005_Lippsinc._Funkytown_1976.mp3",
                    "artist": {
                        "name": "Lipps inc."
                    }
                },
                {
                    "title": "Le freak",
                    "music": "1923_Chic_Lefreak_1978.mp3",
                    "artist": {
                        "name": "Chic"
                    }
                },
                {
                    "title": "The payback",
                    "music": "4112_JamesBrown_Thepayback_1973.mp3",
                    "artist": {
                        "name": "James Brown"
                    }
                },
                {
                    "title": "Spirit in the Dark",
                    "music": "44011_ArethaFranklin_SpiritintheDark_1970.mp3",
                    "artist": {
                        "name": "Aretha Franklin"
                    }
                },
                {
                    "title": "Highway to hell",
                    "music": "70_ACDC_Highwaytohell_1979.mp3",
                    "artist": {
                        "name": "AC/DC"
                    }
                },
                {
                    "title": "Girls Got Rhythm",
                    "music": "41072_ACDC_GirlsGotRhythm_1979.mp3",
                    "artist": {
                        "name": "AC/DC"
                    }
                },
                {
                    "title": "Cheo Feliciano - El Raton",
                    "music": "40730_FaniaAllStars_CheoFeliciano-ElRato_1976.mp3",
                    "artist": {
                        "name": "Fania All Stars"
                    }
                },
                {
                    "title": "Lola",
                    "music": "40679_ChicoBuarque_Lola_1978.mp3",
                    "artist": {
                        "name": "Chico Buarque"
                    }
                },
                {
                    "title": "Pass It On",
                    "music": "45798_BobMarley_PassItOn_1973.mp3",
                    "artist": {
                        "name": "Bob Marley"
                    }
                },
                {
                    "title": "Soul shakedown party",
                    "music": "15359_BobMarley_Soulshakedownparty_1975.mp3",
                    "artist": {
                        "name": "Bob Marley"
                    }
                },
                {
                    "title": "Pressure drop",
                    "music": "12905_TootsandtheMayt_Pressuredrop_1973.mp3",
                    "artist": {
                        "name": "Toots and the Maytals"
                    }
                },
                {
                    "title": "Relax Baby Be Cool",
                    "music": "70577_SergeGainsbourg_RelaxBabyBeCool_1979.mp3",
                    "artist": {
                        "name": "Serge Gainsbourg"
                    }
                },
                {
                    "title": "Mercy Mercy Me",
                    "music": "62617_MarvinGaye_MercyMercyMe_1971.mp3",
                    "artist": {
                        "name": "Marvin Gaye"
                    }
                },
                {
                    "title": "Baby, This Love I Have",
                    "music": "76630_MinnieRiperton_BabyThisLoveIHave_1975.mp3",
                    "artist": {
                        "name": "Minnie Riperton"
                    }
                },
                {
                    "title": "Dancing machine",
                    "music": "4040_TheJacksonFive_Dancingmachine_1973.mp3",
                    "artist": {
                        "name": "The Jackson Five"
                    }
                },
                {
                    "title": "Heart of gold",
                    "music": "5791_NeilYoung_Heartofgold_1972.mp3",
                    "artist": {
                        "name": "Neil Young"
                    }
                },
                {
                    "title": "Northern sky",
                    "music": "5880_NickDrake_Northernsky_1970.mp3",
                    "artist": {
                        "name": "Nick Drake"
                    }
                },
                {
                    "title": "Little green",
                    "music": "4524_JoniMitchell_Littlegreen_1971.mp3",
                    "artist": {
                        "name": "Joni Mitchell"
                    }
                },
                {
                    "title": "Whole Lotta Shakin' Goin' On",
                    "music": "56702_ElvisPresley_WholeLottaShakinGoin_1971.mp3",
                    "artist": {
                        "name": "Elvis Presley"
                    }
                },
                {
                    "title": "Tomorrow Never Comes",
                    "music": "56700_ElvisPresley_TomorrowNeverComes_1971.mp3",
                    "artist": {
                        "name": "Elvis Presley"
                    }
                },
                {
                    "title": "Stand By Me",
                    "music": "36514_RyCooder_StandByMe_1976.mp3",
                    "artist": {
                        "name": "Ry Cooder"
                    }
                },
                {
                    "title": "Faded Love",
                    "music": "56708_ElvisPresley_FadedLove_1971.mp3",
                    "artist": {
                        "name": "Elvis Presley"
                    }
                },
                {
                    "title": "I Washed My Hands In Muddy Water",
                    "music": "56709_ElvisPresley_IWashedMyHandsInMudd_1971.mp3",
                    "artist": {
                        "name": "Elvis Presley"
                    }
                },
                {
                    "title": "Funkytown",
                    "music": "5005_Lippsinc._Funkytown_1976.mp3",
                    "artist": {
                        "name": "Lipps inc."
                    }
                },
                {
                    "title": "Le freak",
                    "music": "1923_Chic_Lefreak_1978.mp3",
                    "artist": {
                        "name": "Chic"
                    }
                },
                {
                    "title": "You should be dancing",
                    "music": "922_TheBeeGees_Youshouldbedancing_1977.mp3",
                    "artist": {
                        "name": "The Bee Gees"
                    }
                },
                {
                    "title": "Blame it on the boogie",
                    "music": "13584_TheJacksonFive_Blameitontheboogie_1978.mp3",
                    "artist": {
                        "name": "The Jackson Five"
                    }
                },
                {
                    "title": "Luv n' haight",
                    "music": "7371_SlyandtheFamily_Luvnhaight_1971.mp3",
                    "artist": {
                        "name": "Sly and the Family Stone"
                    }
                },
                {
                    "title": "Movin'",
                    "music": "58452_BrassConstructi_Movin_1975.mp3",
                    "artist": {
                        "name": "Brass Construction"
                    }
                },
                {
                    "title": "Rockin' Robin",
                    "music": "44223_TheJacksonFive_RockinRobin_1972.mp3",
                    "artist": {
                        "name": "The Jackson Five"
                    }
                },
                {
                    "title": "To Know You Is To Love You",
                    "music": "132990_ThelmaHoustonPr_ToKnowYouIsToLoveYou_1975.mp3",
                    "artist": {
                        "name": "Thelma Houston & Pressure Cooker"
                    }
                },
                {
                    "title": "Apollonia",
                    "music": "78063_TheGodfather_Apollonia_1972.mp3",
                    "artist": {
                        "name": "The Godfather"
                    }
                },
                {
                    "title": "Cavatina",
                    "music": "37424_TheDeerHunter_Cavatina_1978.mp3",
                    "artist": {
                        "name": "The Deer Hunter"
                    }
                },
                {
                    "title": "Guiltiness",
                    "music": "1350_BobMarley_Guiltiness_1977.mp3",
                    "artist": {
                        "name": "Bob Marley"
                    }
                },
                {
                    "title": "Get up, stand up",
                    "music": "1349_BobMarley_Getupstandup_1973.mp3",
                    "artist": {
                        "name": "Bob Marley"
                    }
                },
                {
                    "title": "War",
                    "music": "45861_BobMarley_War_1976.mp3",
                    "artist": {
                        "name": "Bob Marley"
                    }
                },
                {
                    "title": "Invasion",
                    "music": "80701_BurningSpear_Invasion_1976.mp3",
                    "artist": {
                        "name": "Burning Spear"
                    }
                },
                {
                    "title": "Raised On Robbery",
                    "music": "55287_JoniMitchell_RaisedOnRobbery_1974.mp3",
                    "artist": {
                        "name": "Joni Mitchell"
                    }
                },
                {
                    "title": "Whole Lotta Shakin' Goin' On",
                    "music": "56702_ElvisPresley_WholeLottaShakinGoin_1971.mp3",
                    "artist": {
                        "name": "Elvis Presley"
                    }
                },
                {
                    "title": "9 to 5",
                    "music": "2778_DollyParton_9to5_1971.mp3",
                    "artist": {
                        "name": "Dolly Parton"
                    }
                },
                {
                    "title": "Tomorrow Never Comes",
                    "music": "56700_ElvisPresley_TomorrowNeverComes_1971.mp3",
                    "artist": {
                        "name": "Elvis Presley"
                    }
                },
                {
                    "title": "I Washed My Hands In Muddy Water",
                    "music": "56709_ElvisPresley_IWashedMyHandsInMudd_1971.mp3",
                    "artist": {
                        "name": "Elvis Presley"
                    }
                },
                {
                    "title": "Stand By Me",
                    "music": "36514_RyCooder_StandByMe_1976.mp3",
                    "artist": {
                        "name": "Ry Cooder"
                    }
                }
            ]
        },
        {
            "genre": "Les années 1980",
            "media": [
                {
                    "title": "Avalon",
                    "music": "6976_RoxyMusic_Avalon_1982.mp3",
                    "artist": {
                        "name": "Roxy Music"
                    }
                },
                {
                    "title": "Woman",
                    "music": "49957_JohnLennon_Woman_1980.mp3",
                    "artist": {
                        "name": "John Lennon"
                    }
                },
                {
                    "title": "2000 miles",
                    "music": "6427_ThePretenders_2000miles_1984.mp3",
                    "artist": {
                        "name": "The Pretenders"
                    }
                },
                {
                    "title": "Alors regarde",
                    "music": "24278_PatrickBruel_Alorsregarde_1989.mp3",
                    "artist": {
                        "name": "Patrick Bruel"
                    }
                },
                {
                    "title": "Dr. beat",
                    "music": "13980_GloriaEstefan_Dr.beat_1984.mp3",
                    "artist": {
                        "name": "Gloria Estefan"
                    }
                },
                {
                    "title": "I'm real",
                    "music": "4094_JamesBrown_Imreal_1988.mp3",
                    "artist": {
                        "name": "James Brown"
                    }
                },
                {
                    "title": "The Duellists",
                    "music": "61785_IronMaiden_TheDuellists_1984.mp3",
                    "artist": {
                        "name": "Iron Maiden"
                    }
                },
                {
                    "title": "You Shook Me All Night Long",
                    "music": "41087_ACDC_YouShookMeAllNightLo_1980.mp3",
                    "artist": {
                        "name": "AC/DC"
                    }
                },
                {
                    "title": "Crossfire",
                    "music": "77583_StevieRayVaugha_Crossfire_1989.mp3",
                    "artist": {
                        "name": "Stevie Ray Vaughan"
                    }
                },
                {
                    "title": "I'm Cryin'",
                    "music": "77557_StevieRayVaugha_ImCryin_1983.mp3",
                    "artist": {
                        "name": "Stevie Ray Vaughan"
                    }
                },
                {
                    "title": "Voodo Chile (Slight Return)",
                    "music": "77579_StevieRayVaugha_VoodoChile(SlightRet_1986.mp3",
                    "artist": {
                        "name": "Stevie Ray Vaughan"
                    }
                },
                {
                    "title": "Looking Down the Barrel of a Gun",
                    "music": "44417_TheBeastieBoys_LookingDowntheBarrel_1989.mp3",
                    "artist": {
                        "name": "The Beastie Boys"
                    }
                },
                {
                    "title": "Fight For Your Right",
                    "music": "44401_TheBeastieBoys_FightForYourRight_1986.mp3",
                    "artist": {
                        "name": "The Beastie Boys"
                    }
                },
                {
                    "title": "Chi Mai",
                    "music": "3124_EnnioMorricone_ChiMai_1981.mp3",
                    "artist": {
                        "name": "Ennio Morricone"
                    }
                },
                {
                    "title": "Wanted Dread & Alive",
                    "music": "81708_PeterTosh_WantedDreadAlive_1981.mp3",
                    "artist": {
                        "name": "Peter Tosh"
                    }
                },
                {
                    "title": "Fear Of Falling",
                    "music": "111679_CuttingCrew_FearOfFalling_1986.mp3",
                    "artist": {
                        "name": "Cutting Crew"
                    }
                },
                {
                    "title": "Can't take my eyes off you",
                    "music": "1444_BoysTownGang_Canttakemyeyesoffyou_1982.mp3",
                    "artist": {
                        "name": "Boys Town Gang"
                    }
                },
                {
                    "title": "Stayin' alive",
                    "music": "916_TheBeeGees_Stayinalive_1983.mp3",
                    "artist": {
                        "name": "The Bee Gees"
                    }
                },
                {
                    "title": "Purple rain",
                    "music": "6496_Prince_Purplerain_1984.mp3",
                    "artist": {
                        "name": "Prince"
                    }
                },
                {
                    "title": "I would die for you",
                    "music": "6482_Prince_Iwoulddieforyou_1984.mp3",
                    "artist": {
                        "name": "Prince"
                    }
                },
                {
                    "title": "You Shook Me All Night Long",
                    "music": "41087_ACDC_YouShookMeAllNightLo_1980.mp3",
                    "artist": {
                        "name": "AC/DC"
                    }
                },
                {
                    "title": "Cum on feel the noize",
                    "music": "14084_QuietRiot_Cumonfeelthenoize_1983.mp3",
                    "artist": {
                        "name": "Quiet Riot"
                    }
                },
                {
                    "title": "I want to say",
                    "music": "34587_StanGetz_Iwanttosay_1986.mp3",
                    "artist": {
                        "name": "Stan Getz"
                    }
                },
                {
                    "title": "Me Deixa Louca (Me Vuelves Loco)",
                    "music": "124320_ElisRegina_MeDeixaLouca(MeVuelv_1981.mp3",
                    "artist": {
                        "name": "Elis Regina"
                    }
                },
                {
                    "title": "Take my breath away (love theme from 'top gun')",
                    "music": "9251_Topgun_Takemybreathaway(lov_1986.mp3",
                    "artist": {
                        "name": "Top gun"
                    }
                },
                {
                    "title": "Give me the night",
                    "music": "3580_GeorgeBenson_Givemethenight_1980.mp3",
                    "artist": {
                        "name": "George Benson"
                    }
                },
                {
                    "title": "One Irish Rover",
                    "music": "67212_VanMorrison_OneIrishRover_1986.mp3",
                    "artist": {
                        "name": "Van Morrison"
                    }
                },
                {
                    "title": "Goodbye windflower",
                    "music": "2715_DireStraits_Goodbyewindflower_1985.mp3",
                    "artist": {
                        "name": "Dire Straits"
                    }
                },
                {
                    "title": "Via con me",
                    "music": "24668_PaoloConte_Viaconme_1985.mp3",
                    "artist": {
                        "name": "Paolo Conte"
                    }
                },
                {
                    "title": "Boogie",
                    "music": "24260_PaoloConte_Boogie_1985.mp3",
                    "artist": {
                        "name": "Paolo Conte"
                    }
                },
                {
                    "title": "Joe le taxi",
                    "music": "8610_VanessaParadis_Joeletaxi_1987.mp3",
                    "artist": {
                        "name": "Vanessa Paradis"
                    }
                },
                {
                    "title": "Stayin' alive",
                    "music": "916_TheBeeGees_Stayinalive_1983.mp3",
                    "artist": {
                        "name": "The Bee Gees"
                    }
                },
                {
                    "title": "I'm real",
                    "music": "4094_JamesBrown_Imreal_1988.mp3",
                    "artist": {
                        "name": "James Brown"
                    }
                },
                {
                    "title": "I'll never turn my back on you",
                    "music": "7776_TerenceTrentdAr_Illneverturnmybackon_1987.mp3",
                    "artist": {
                        "name": "Terence Trent d'Arby"
                    }
                },
                {
                    "title": "The Map Room Dawn",
                    "music": "37313_RaidersOfTheLos_TheMapRoomDawn_1981.mp3",
                    "artist": {
                        "name": "Raiders Of The Lost Ark"
                    }
                },
                {
                    "title": "Redemption song",
                    "music": "1358_BobMarley_Redemptionsong_1980.mp3",
                    "artist": {
                        "name": "Bob Marley"
                    }
                },
                {
                    "title": "Jah Houphouet",
                    "music": "346_AlphaBlondy_JahHouphouet_1987.mp3",
                    "artist": {
                        "name": "Alpha Blondy"
                    }
                },
                {
                    "title": "Everybody Needs Somebody to Love",
                    "music": "1272_TheBluesBrother_EverybodyNeedsSomebo_1980.mp3",
                    "artist": {
                        "name": "The Blues Brothers"
                    }
                },
                {
                    "title": "Highway 61 revisited",
                    "music": "12797_BobDylan_Highway61revisited_1983.mp3",
                    "artist": {
                        "name": "Bob Dylan"
                    }
                }
            ]
        },
        {
            "genre": "Les années 1990",
            "media": [
                {
                    "title": "Bitter sweet symphony",
                    "music": "8150_TheVerve_Bittersweetsymphony_1997.mp3",
                    "artist": {
                        "name": "The Verve"
                    }
                },
                {
                    "title": "Belong",
                    "music": "6588_R.E.M._Belong_1991.mp3",
                    "artist": {
                        "name": "R.E.M."
                    }
                },
                {
                    "title": "Hero",
                    "music": "2473_DavidCrosby_Hero_1993.mp3",
                    "artist": {
                        "name": "David Crosby"
                    }
                },
                {
                    "title": "Secret",
                    "music": "6059_Madonna_Secret_1994.mp3",
                    "artist": {
                        "name": "Madonna"
                    }
                },
                {
                    "title": "Zen",
                    "music": "8358_Zazie_Zen_1996.mp3",
                    "artist": {
                        "name": "Zazie"
                    }
                },
                {
                    "title": "La Cabane du Pêcheur",
                    "music": "23712_FrancisCabrel_LaCabaneduP234cheur_1995.mp3",
                    "artist": {
                        "name": "Francis Cabrel"
                    }
                },
                {
                    "title": "Firestarter",
                    "music": "59691_TheProdigy_Firestarter_1997.mp3",
                    "artist": {
                        "name": "The Prodigy"
                    }
                },
                {
                    "title": "B Line",
                    "music": "96868_Lamb_BLine_1999.mp3",
                    "artist": {
                        "name": "Lamb"
                    }
                },
                {
                    "title": "Serial Thrilla",
                    "music": "59688_TheProdigy_SerialThrilla_1997.mp3",
                    "artist": {
                        "name": "The Prodigy"
                    }
                },
                {
                    "title": "Could It Be Magic",
                    "music": "75453_DonnaSummer_CouldItBeMagic_1994.mp3",
                    "artist": {
                        "name": "Donna Summer"
                    }
                },
                {
                    "title": "King for a day",
                    "music": "4136_Jamiroquai_Kingforaday_1999.mp3",
                    "artist": {
                        "name": "Jamiroquai"
                    }
                },
                {
                    "title": "Emergency On Planet Earth",
                    "music": "39236_Jamiroquai_EmergencyOnPlanetEar_1993.mp3",
                    "artist": {
                        "name": "Jamiroquai"
                    }
                },
                {
                    "title": "Million miles from home",
                    "music": "4666_KeziahJones_Millionmilesfromhome_1995.mp3",
                    "artist": {
                        "name": "Keziah Jones"
                    }
                },
                {
                    "title": "So much trouble in my mind",
                    "music": "8800_SirJoeQuarterma_Somuchtroubleinmymin_1995.mp3",
                    "artist": {
                        "name": "Sir Joe Quarterman and Free Soul"
                    }
                },
                {
                    "title": "Your Child",
                    "music": "21414_MaryJ.Blige_YourChild_1999.mp3",
                    "artist": {
                        "name": "Mary J. Blige"
                    }
                },
                {
                    "title": "Yesterdays",
                    "music": "41741_GunsNRoses_Yesterdays_1991.mp3",
                    "artist": {
                        "name": "Guns N'Roses"
                    }
                },
                {
                    "title": "Greatest of all time",
                    "music": "5039_LlCoolJ_Greatestofalltime_1995.mp3",
                    "artist": {
                        "name": "Ll Cool J"
                    }
                },
                {
                    "title": "La fièvre",
                    "music": "7657_SuprmeNTM_Lafi232vre_1995.mp3",
                    "artist": {
                        "name": "Suprême NTM"
                    }
                },
                {
                    "title": "La Gloria Eres Tu",
                    "music": "98646_RubnGonzlez_LaGloriaEresTu_1998.mp3",
                    "artist": {
                        "name": "Rubén González"
                    }
                },
                {
                    "title": "De camino a la vereda",
                    "music": "1559_BuenaVistaSocia_Decaminoalavereda_1997.mp3",
                    "artist": {
                        "name": "Buena Vista Social Club"
                    }
                },
                {
                    "title": "Tres Lindas Cubanas",
                    "music": "20514_RubnGonzlez_TresLindasCubanas_1997.mp3",
                    "artist": {
                        "name": "Rubén González"
                    }
                },
                {
                    "title": "Melodia del Rio",
                    "music": "20515_RubnGonzlez_MelodiadelRio_1997.mp3",
                    "artist": {
                        "name": "Rubén González"
                    }
                },
                {
                    "title": "Lunch w-The King",
                    "music": "113541_AmericanBeauty_Lunchw-TheKing_1999.mp3",
                    "artist": {
                        "name": "American Beauty"
                    }
                },
                {
                    "title": "Sorry sorry",
                    "music": "3364_FemiKuti_Sorrysorry_1999.mp3",
                    "artist": {
                        "name": "Femi Kuti"
                    }
                },
                {
                    "title": "Wakafrica",
                    "music": "5254_ManuDibango_Wakafrica_1994.mp3",
                    "artist": {
                        "name": "Manu Dibango"
                    }
                },
                {
                    "title": "You are the sunshine of my life",
                    "music": "7587_StevieWonder_Youarethesunshineofm_1995.mp3",
                    "artist": {
                        "name": "Stevie Wonder"
                    }
                },
                {
                    "title": "Natural Beauty",
                    "music": "55814_NeilYoung_NaturalBeauty_1992.mp3",
                    "artist": {
                        "name": "Neil Young"
                    }
                },
                {
                    "title": "Ana",
                    "music": "50890_Pixies_Ana_1990.mp3",
                    "artist": {
                        "name": "Pixies"
                    }
                },
                {
                    "title": "Head over feet (acoustic) @ Acoustic",
                    "music": "226_AlanisMorissett_Headoverfeet(acousti_1995.mp3",
                    "artist": {
                        "name": "Alanis Morissette"
                    }
                },
                {
                    "title": "Sugarcoated",
                    "music": "67419_AimeeMann_Sugarcoated_1996.mp3",
                    "artist": {
                        "name": "Aimee Mann"
                    }
                },
                {
                    "title": "Le complexe du corn flakes",
                    "music": "73696_MathieuChedid_Lecomplexeducornflak_1999.mp3",
                    "artist": {
                        "name": "Mathieu Chedid"
                    }
                },
                {
                    "title": "Stem Long Stem Transmission 2",
                    "music": "59330_DJShadow_StemLongStemTransmis_1996.mp3",
                    "artist": {
                        "name": "DJ Shadow"
                    }
                },
                {
                    "title": "Exterminate (Endzeit 7'')",
                    "music": "131730_Snap_Exterminate(Endzeit7_1992.mp3",
                    "artist": {
                        "name": "Snap!"
                    }
                },
                {
                    "title": "Brazil",
                    "music": "164139_RitchieFamily_Brazil_1991.mp3",
                    "artist": {
                        "name": "Ritchie Family"
                    }
                },
                {
                    "title": "Babylon",
                    "music": "86149_Edguy_Babylon_1999.mp3",
                    "artist": {
                        "name": "Edguy"
                    }
                },
                {
                    "title": "I Wanna Be Sedated (live)",
                    "music": "42143_TheRamones_IWannaBeSedated(live_1991.mp3",
                    "artist": {
                        "name": "The Ramones"
                    }
                },
                {
                    "title": "She Puts Me In The Mood",
                    "music": "76867_ElvinBishop_ShePutsMeInTheMood_1996.mp3",
                    "artist": {
                        "name": "Elvin Bishop"
                    }
                },
                {
                    "title": "Isis",
                    "music": "77322_PopaChubby_Isis_1996.mp3",
                    "artist": {
                        "name": "Popa Chubby"
                    }
                },
                {
                    "title": "Big Brother Beat",
                    "music": "44719_DeLaSoul_BigBrotherBeat_1996.mp3",
                    "artist": {
                        "name": "De La Soul"
                    }
                },
                {
                    "title": "Unbelievable",
                    "music": "71778_TheNotoriousB.I_Unbelievable_1994.mp3",
                    "artist": {
                        "name": "The Notorious B.I.G."
                    }
                },
                {
                    "title": "work",
                    "music": "71054_GangStarr_work_1998.mp3",
                    "artist": {
                        "name": "Gang Starr"
                    }
                },
                {
                    "title": "Electric Relaxation",
                    "music": "44327_ATribeCalledQue_ElectricRelaxation_1993.mp3",
                    "artist": {
                        "name": "A Tribe Called Quest"
                    }
                },
                {
                    "title": "Brakes",
                    "music": "44712_DeLaSoul_Brakes_1996.mp3",
                    "artist": {
                        "name": "De La Soul"
                    }
                },
                {
                    "title": "Wishibn' and hopin'",
                    "music": "12349_AniDifranco_Wishibnandhopin_1997.mp3",
                    "artist": {
                        "name": "Ani Difranco"
                    }
                },
                {
                    "title": "Alegria",
                    "music": "113651_CirqueDuSoleil_Alegria_1994.mp3",
                    "artist": {
                        "name": "Cirque Du Soleil"
                    }
                },
                {
                    "title": "Truth don die",
                    "music": "3365_FemiKuti_Truthdondie_1999.mp3",
                    "artist": {
                        "name": "Femi Kuti"
                    }
                },
                {
                    "title": "Yelele",
                    "music": "4596_Kassav_Yelele_1999.mp3",
                    "artist": {
                        "name": "Kassav'"
                    }
                },
                {
                    "title": "Qalbi",
                    "music": "392_AmrDiabChebKhal_Qalbi_1994.mp3",
                    "artist": {
                        "name": "Amr Diab & Cheb Khaled"
                    }
                },
                {
                    "title": "Pomps And Pride",
                    "music": "82201_TootsandtheMayt_PompsAndPride_1999.mp3",
                    "artist": {
                        "name": "Toots and the Maytals"
                    }
                },
                {
                    "title": "Children under the sun",
                    "music": "81158_IsraelVibration_Childrenunderthesun_1991.mp3",
                    "artist": {
                        "name": "Israel Vibration"
                    }
                },
                {
                    "title": "Waiting for the miracle",
                    "music": "4969_LeonardCohen_Waitingforthemiracle_1992.mp3",
                    "artist": {
                        "name": "Leonard Cohen"
                    }
                },
                {
                    "title": "The three of us",
                    "music": "979_BenHarper_Thethreeofus_1994.mp3",
                    "artist": {
                        "name": "Ben Harper"
                    }
                },
                {
                    "title": "Overdose (D'amore)",
                    "music": "24478_Zucchero_Overdose(Damore)_1996.mp3",
                    "artist": {
                        "name": "Zucchero"
                    }
                },
                {
                    "title": "All I Need",
                    "music": "38229_Air_AllINeed_1998.mp3",
                    "artist": {
                        "name": "Air"
                    }
                },
                {
                    "title": "Eden ?",
                    "music": "13057_Hooverphonic_Eden_1998.mp3",
                    "artist": {
                        "name": "Hooverphonic"
                    }
                },
                {
                    "title": "You're not alone",
                    "music": "6045_Olive_Yourenotalone_1996.mp3",
                    "artist": {
                        "name": "Olive"
                    }
                },
                {
                    "title": "Mr Moon",
                    "music": "39247_Jamiroquai_MrMoon_1994.mp3",
                    "artist": {
                        "name": "Jamiroquai"
                    }
                },
                {
                    "title": "Mandylion",
                    "music": "66513_TheGathering_Mandylion_1995.mp3",
                    "artist": {
                        "name": "The Gathering"
                    }
                },
                {
                    "title": "Walking In The Air",
                    "music": "61976_Nightwish_WalkingInTheAir_1998.mp3",
                    "artist": {
                        "name": "Nightwish"
                    }
                },
                {
                    "title": "Shoota babylone",
                    "music": "12381_Assassin_Shootababylone_1996.mp3",
                    "artist": {
                        "name": "Assassin"
                    }
                },
                {
                    "title": "Ready Or Not",
                    "music": "83438_TheFugees_ReadyOrNot_1996.mp3",
                    "artist": {
                        "name": "The Fugees"
                    }
                },
                {
                    "title": "Alguem me avisou",
                    "music": "13289_MariaBethnia_Alguemmeavisou_1996.mp3",
                    "artist": {
                        "name": "Maria Bethânia"
                    }
                },
                {
                    "title": "Quem Te Viu Quem Te Vê",
                    "music": "40690_ChicoBuarque_QuemTeViuQuemTeV234_1997.mp3",
                    "artist": {
                        "name": "Chico Buarque"
                    }
                },
                {
                    "title": "Sorry sorry",
                    "music": "3364_FemiKuti_Sorrysorry_1999.mp3",
                    "artist": {
                        "name": "Femi Kuti"
                    }
                },
                {
                    "title": "Wakafrica",
                    "music": "5254_ManuDibango_Wakafrica_1994.mp3",
                    "artist": {
                        "name": "Manu Dibango"
                    }
                },
                {
                    "title": "Jingo",
                    "music": "5250_ManuDibango_Jingo_1994.mp3",
                    "artist": {
                        "name": "Manu Dibango"
                    }
                }
            ]
        },
        {
            "genre": "Les années 2000",
            "media": [
                {
                    "title": "She will be loved",
                    "music": "5317_Maroon5_Shewillbeloved_2004.mp3",
                    "artist": {
                        "name": "Maroon 5"
                    }
                },
                {
                    "title": "Tout Le Bonheur Du Monde",
                    "music": "7339_Sinsemilia_ToutLeBonheurDuMonde_2005.mp3",
                    "artist": {
                        "name": "Sinsemilia"
                    }
                },
                {
                    "title": "Je pourrais",
                    "music": "9011_Eva_Jepourrais_2006.mp3",
                    "artist": {
                        "name": "Eva"
                    }
                },
                {
                    "title": "Impossible",
                    "music": "14644_LaRueKetanou_Impossible_2004.mp3",
                    "artist": {
                        "name": "La Rue Ketanou"
                    }
                },
                {
                    "title": "Stress",
                    "music": "20137_Justice_Stress_2007.mp3",
                    "artist": {
                        "name": "Justice"
                    }
                },
                {
                    "title": "Sacramento",
                    "music": "110773_DeepDish_Sacramento_2005.mp3",
                    "artist": {
                        "name": "Deep Dish"
                    }
                },
                {
                    "title": "Stop Don't Panic",
                    "music": "39282_Jamiroquai_StopDontPanic_2001.mp3",
                    "artist": {
                        "name": "Jamiroquai"
                    }
                },
                {
                    "title": "Fallin Out",
                    "music": "99281_KeyshiaCole_FallinOut_2007.mp3",
                    "artist": {
                        "name": "Keyshia Cole"
                    }
                },
                {
                    "title": "Love Don't Live Here Anymore",
                    "music": "61328_PattiLabelle_LoveDontLiveHereAnym_2005.mp3",
                    "artist": {
                        "name": "Patti Labelle"
                    }
                },
                {
                    "title": "Ain't No Way f. Mary J. Blige",
                    "music": "61325_PattiLabelle_AintNoWayf.MaryJ.Bli_2005.mp3",
                    "artist": {
                        "name": "Patti Labelle"
                    }
                },
                {
                    "title": "Silly",
                    "music": "61334_PattiLabelle_Silly_2005.mp3",
                    "artist": {
                        "name": "Patti Labelle"
                    }
                },
                {
                    "title": "Worshipper In Me",
                    "music": "96000_MarvinSapp_WorshipperInMe_2007.mp3",
                    "artist": {
                        "name": "Marvin Sapp"
                    }
                },
                {
                    "title": "No Place To Run",
                    "music": "125539_GymClassHeroes_NoPlaceToRun_2008.mp3",
                    "artist": {
                        "name": "Gym Class Heroes"
                    }
                },
                {
                    "title": "Lose yourself",
                    "music": "3080_Eminem_Loseyourself_2002.mp3",
                    "artist": {
                        "name": "Eminem"
                    }
                },
                {
                    "title": "Linda Flor (Yayá) (Ai, Yoyô)",
                    "music": "40772_GalCosta_LindaFlor(Yay225)(Ai_2004.mp3",
                    "artist": {
                        "name": "Gal Costa"
                    }
                },
                {
                    "title": "Highschool Lover @ Instrumental",
                    "music": "37607_TheVirginSuicid_HighschoolLoverInstr_2000.mp3",
                    "artist": {
                        "name": "The Virgin Suicides"
                    }
                },
                {
                    "title": "Flightless Bird, American Mouth",
                    "music": "143925_Twilight_FlightlessBirdAmeric_2008.mp3",
                    "artist": {
                        "name": "Twilight"
                    }
                },
                {
                    "title": "Aicha",
                    "music": "56091_ChebKhaledRachi_Aicha_2000.mp3",
                    "artist": {
                        "name": "Cheb Khaled & Rachid Taha"
                    }
                },
                {
                    "title": "Machine Gun",
                    "music": "56136_ManuChao_MachineGun_2002.mp3",
                    "artist": {
                        "name": "Manu Chao"
                    }
                },
                {
                    "title": "Traitors of africa",
                    "music": "100275_FemiKuti_Traitorsofafrica_2002.mp3",
                    "artist": {
                        "name": "Femi Kuti"
                    }
                },
                {
                    "title": "Stir It Up",
                    "music": "82462_ZiggyMarley_StirItUp_2000.mp3",
                    "artist": {
                        "name": "Ziggy Marley"
                    }
                },
                {
                    "title": "Sunshine",
                    "music": "81678_Patrice_Sunshine_2002.mp3",
                    "artist": {
                        "name": "Patrice"
                    }
                },
                {
                    "title": "I'm Yours",
                    "music": "95609_JasonMraz_ImYours_2008.mp3",
                    "artist": {
                        "name": "Jason Mraz"
                    }
                },
                {
                    "title": "Make It Mine",
                    "music": "161824_JasonMraz_MakeItMine_2008.mp3",
                    "artist": {
                        "name": "Jason Mraz"
                    }
                },
                {
                    "title": "Makes me wonder",
                    "music": "15468_Maroon5_Makesmewonder_2007.mp3",
                    "artist": {
                        "name": "Maroon 5"
                    }
                },
                {
                    "title": "Nails For Breakfast Tacks For Snacks",
                    "music": "130559_PanicAtTheDisco_NailsForBreakfastTac_2007.mp3",
                    "artist": {
                        "name": "Panic At The Disco"
                    }
                },
                {
                    "title": "I Want I Want",
                    "music": "96419_Digitalism_IWantIWant_2007.mp3",
                    "artist": {
                        "name": "Digitalism"
                    }
                },
                {
                    "title": "Now That We're Done",
                    "music": "97015_MetroStation_NowThatWereDone_2007.mp3",
                    "artist": {
                        "name": "Metro Station"
                    }
                },
                {
                    "title": "So Haunted",
                    "music": "96370_CutCopy_SoHaunted_2008.mp3",
                    "artist": {
                        "name": "Cut Copy"
                    }
                },
                {
                    "title": "I Am A Freak",
                    "music": "97407_YoungerBrother_IAmAFreak_2007.mp3",
                    "artist": {
                        "name": "Younger Brother"
                    }
                },
                {
                    "title": "I Guess Thats Why They Call It The Blues Ft.Elton John",
                    "music": "21472_MaryJ.Blige_IGuessThatsWhyTheyCa_2006.mp3",
                    "artist": {
                        "name": "Mary J. Blige"
                    }
                },
                {
                    "title": "SOS",
                    "music": "8738_Rihanna_SOS_2006.mp3",
                    "artist": {
                        "name": "Rihanna"
                    }
                },
                {
                    "title": "Green Light (Feat. Andre 3000)",
                    "music": "126383_JohnLegend_GreenLight(Feat.Andr_2008.mp3",
                    "artist": {
                        "name": "John Legend"
                    }
                },
                {
                    "title": "Let me",
                    "music": "9052_Rihanna_Letme_2006.mp3",
                    "artist": {
                        "name": "Rihanna"
                    }
                },
                {
                    "title": "Disturbia",
                    "music": "141371_Rihanna_Disturbia_2008.mp3",
                    "artist": {
                        "name": "Rihanna"
                    }
                },
                {
                    "title": "Worshipper In Me",
                    "music": "96000_MarvinSapp_WorshipperInMe_2007.mp3",
                    "artist": {
                        "name": "Marvin Sapp"
                    }
                },
                {
                    "title": "Innamorata",
                    "music": "31006_AlDiMeola_Innamorata_2002.mp3",
                    "artist": {
                        "name": "Al DiMeola"
                    }
                },
                {
                    "title": "Slacker",
                    "music": "104049_TechN9ne_Slacker_2003.mp3",
                    "artist": {
                        "name": "Tech N9ne"
                    }
                },
                {
                    "title": "Obsesión",
                    "music": "651_Aventura_Obsesi243n_2002.mp3",
                    "artist": {
                        "name": "Aventura"
                    }
                },
                {
                    "title": "Como Me Duele Perderte",
                    "music": "125382_GloriaEstefan_ComoMeDuelePerderte_2000.mp3",
                    "artist": {
                        "name": "Gloria Estefan"
                    }
                },
                {
                    "title": "Going To School",
                    "music": "37175_MemoirsOfAGeish_GoingToSchool_2005.mp3",
                    "artist": {
                        "name": "Memoirs Of A Geisha"
                    }
                },
                {
                    "title": "La valse d'Amélie (version orchestre)",
                    "music": "37045_Lefabuleuxdesti_LavalsedAm233lie(ver_2001.mp3",
                    "artist": {
                        "name": "Le fabuleux destin d'Amélie Poulain"
                    }
                },
                {
                    "title": "Abdel Kader",
                    "music": "56090_ChebKhaledRachi_AbdelKader_2000.mp3",
                    "artist": {
                        "name": "Cheb Khaled & Rachid Taha"
                    }
                },
                {
                    "title": "Laisse parler les gens",
                    "music": "4344_JocelyneLabylle_Laisseparlerlesgens_2004.mp3",
                    "artist": {
                        "name": "Jocelyne Labylle"
                    }
                },
                {
                    "title": "Birima",
                    "music": "101096_YoussouNDour_Birima_2000.mp3",
                    "artist": {
                        "name": "Youssou N'Dour"
                    }
                },
                {
                    "title": "Time After Time",
                    "music": "95532_EvaCassidy_TimeAfterTime_2000.mp3",
                    "artist": {
                        "name": "Eva Cassidy"
                    }
                },
                {
                    "title": "Kid A",
                    "music": "6628_Radiohead_KidA_2000.mp3",
                    "artist": {
                        "name": "Radiohead"
                    }
                },
                {
                    "title": "In the Cold, Cold Night",
                    "music": "23193_TheWhiteStripes_IntheColdColdNight_2003.mp3",
                    "artist": {
                        "name": "The White Stripes"
                    }
                },
                {
                    "title": "Save You",
                    "music": "74664_SimplePlan_SaveYou_2008.mp3",
                    "artist": {
                        "name": "Simple Plan"
                    }
                },
                {
                    "title": "Dirrty Ft Redman",
                    "music": "20689_ChristinaAguile_DirrtyFtRedman_2002.mp3",
                    "artist": {
                        "name": "Christina Aguilera"
                    }
                },
                {
                    "title": "Everywhere",
                    "music": "73857_MichelleBranch_Everywhere_2002.mp3",
                    "artist": {
                        "name": "Michelle Branch"
                    }
                },
                {
                    "title": "Bubble pop electrinic feat Johnny Vulture",
                    "music": "68069_GwenStefani_Bubblepopelectrinicf_2004.mp3",
                    "artist": {
                        "name": "Gwen Stefani"
                    }
                },
                {
                    "title": "Sexy No No No...",
                    "music": "73211_GirlsAloud_SexyNoNoNo..._2007.mp3",
                    "artist": {
                        "name": "Girls Aloud"
                    }
                },
                {
                    "title": "La tribu de dana",
                    "music": "9186_Manau_Latribudedana_2001.mp3",
                    "artist": {
                        "name": "Manau"
                    }
                },
                {
                    "title": "Chunga's revenge",
                    "music": "3722_GotanProject_Chungasrevenge_2001.mp3",
                    "artist": {
                        "name": "Gotan Project"
                    }
                },
                {
                    "title": "Frosti",
                    "music": "1196_Bjrk_Frosti_2001.mp3",
                    "artist": {
                        "name": "Björk"
                    }
                },
                {
                    "title": "Miðvikudags",
                    "music": "38455_Bjrk_Mi240vikudags_2004.mp3",
                    "artist": {
                        "name": "Björk"
                    }
                },
                {
                    "title": "All About the Papers",
                    "music": "38221_LoleattaHollowa_AllAboutthePapers_2003.mp3",
                    "artist": {
                        "name": "Loleatta Holloway"
                    }
                },
                {
                    "title": "Stop Don't Panic",
                    "music": "39282_Jamiroquai_StopDontPanic_2001.mp3",
                    "artist": {
                        "name": "Jamiroquai"
                    }
                },
                {
                    "title": "Crazy in love",
                    "music": "1036_Beyonc_Crazyinlove_2003.mp3",
                    "artist": {
                        "name": "Beyoncé"
                    }
                },
                {
                    "title": "I Guess Thats Why They Call It The Blues Ft.Elton John",
                    "music": "21472_MaryJ.Blige_IGuessThatsWhyTheyCa_2006.mp3",
                    "artist": {
                        "name": "Mary J. Blige"
                    }
                },
                {
                    "title": "Eos",
                    "music": "160736_Ulver_Eos_2007.mp3",
                    "artist": {
                        "name": "Ulver"
                    }
                },
                {
                    "title": "Intension",
                    "music": "42214_Tool_Intension_2006.mp3",
                    "artist": {
                        "name": "Tool"
                    }
                },
                {
                    "title": "Etiainen (Unreleased Track)",
                    "music": "86393_Nightwish_Etiainen(UnreleasedT_2005.mp3",
                    "artist": {
                        "name": "Nightwish"
                    }
                },
                {
                    "title": "Teenager",
                    "music": "41686_Deftones_Teenager_2000.mp3",
                    "artist": {
                        "name": "Deftones"
                    }
                },
                {
                    "title": "(I Love You) For Sentimental Reasons",
                    "music": "36007_B.B.King_(ILoveYou)ForSentime_2003.mp3",
                    "artist": {
                        "name": "B.B. King"
                    }
                },
                {
                    "title": "I Wanna Be",
                    "music": "76886_B.B.KingEricCla_IWannaBe_2000.mp3",
                    "artist": {
                        "name": "B.B. King & Eric Clapton"
                    }
                },
                {
                    "title": "Fergalicious",
                    "music": "15167_Fergie_Fergalicious_2007.mp3",
                    "artist": {
                        "name": "Fergie"
                    }
                },
                {
                    "title": "I wonder",
                    "music": "45011_KanyeWest_Iwonder_2007.mp3",
                    "artist": {
                        "name": "Kanye West"
                    }
                },
                {
                    "title": "On My Own Time",
                    "music": "44969_GymClassHeroes_OnMyOwnTime_2007.mp3",
                    "artist": {
                        "name": "Gym Class Heroes"
                    }
                },
                {
                    "title": "Jezebel",
                    "music": "83330_DizzeeRascal_Jezebel_2003.mp3",
                    "artist": {
                        "name": "Dizzee Rascal"
                    }
                },
                {
                    "title": "Emigrantes",
                    "music": "130519_Orishas_Emigrantes_2007.mp3",
                    "artist": {
                        "name": "Orishas"
                    }
                },
                {
                    "title": "Sevillanas Pink",
                    "music": "60762_LasKetchup_SevillanasPink_2002.mp3",
                    "artist": {
                        "name": "Las Ketchup"
                    }
                },
                {
                    "title": "Le moulin",
                    "music": "37043_Lefabuleuxdesti_Lemoulin_2001.mp3",
                    "artist": {
                        "name": "Le fabuleux destin d'Amélie Poulain"
                    }
                },
                {
                    "title": "Traitors of africa",
                    "music": "100275_FemiKuti_Traitorsofafrica_2002.mp3",
                    "artist": {
                        "name": "Femi Kuti"
                    }
                },
                {
                    "title": "Abdel Kader",
                    "music": "56090_ChebKhaledRachi_AbdelKader_2000.mp3",
                    "artist": {
                        "name": "Cheb Khaled & Rachid Taha"
                    }
                }
            ]
        }
    ]
}